imdir.py
imdir-0.2.dist-info/METADATA
imdir-0.2.dist-info/WHEEL
imdir-0.2.dist-info/top_level.txt
imdir-0.2.dist-info/RECORD
