Metadata-Version: 2.1
Name: imdir
Version: 0.2
Summary: A package to analyse a directory full of images
Home-page: https://github.com/dhananjayraut/imdir
Author: Dhananjay Raut
Author-email: rautdhananjay33@gmail.com
License: UNKNOWN
Platform: UNKNOWN
Classifier: Programming Language :: Python :: 3
Classifier: License :: OSI Approved :: MIT License
Classifier: Operating System :: OS Independent
Requires-Dist: pillow
Requires-Dist: matplotlib
